advtok/__init__.py
advtok/evaluate.py
advtok/jailbreak.py
advtok/mdd.py
advtok/multi_rooted_mdd.py
advtok/search.py
advtok/utils.py
advtok-0.0.5.dist-info/LICENSE
advtok-0.0.5.dist-info/METADATA
advtok-0.0.5.dist-info/WHEEL
advtok-0.0.5.dist-info/top_level.txt
advtok-0.0.5.dist-info/RECORD
