Metadata-Version: 2.2
Name: advtok
Version: 0.0.5
Summary: Adversarial Tokenization
Author-email: Renato Lui Geh <renatolg@cs.ucla.edu>, Zilei Shao <zileishao@g.ucla.edu>
Project-URL: Homepage, https://advtok.github.io/
Project-URL: Repository, https://github.com/RenatoGeh/advtok
Project-URL: Issues, https://github.com/RenatoGeh/advtok/issues
Classifier: License :: OSI Approved :: MIT License
Classifier: Programming Language :: Python :: 3
Classifier: Operating System :: POSIX :: Linux
Classifier: Intended Audience :: Science/Research
Classifier: Topic :: Scientific/Engineering :: Artificial Intelligence
Requires-Python: >=3.10.12
License-File: LICENSE
Requires-Dist: accelerate>=1.4.0
Requires-Dist: Levenshtein>=0.26.1
Requires-Dist: torch>=2.6.0
Requires-Dist: transformers>=4.47.1
Requires-Dist: graphviz>=0.20.3
Requires-Dist: numpy<=1.26.4
Requires-Dist: tqdm>=4.67.1
